timemclust/__init__.py
timemclust/em_alg.py
timemclust/exponential_hawkes.py
timemclust/helper.py
timemclust/simulations.py
timemclust/tweet_getter.py
timemclust-0.0.1.2.dist-info/METADATA
timemclust-0.0.1.2.dist-info/WHEEL
timemclust-0.0.1.2.dist-info/top_level.txt
timemclust-0.0.1.2.dist-info/RECORD
